glored/__init__.py
glored/fast_thread_pool.py
glored/interface.py
glored-0.1.1.dist-info/LICENSE
glored-0.1.1.dist-info/METADATA
glored-0.1.1.dist-info/WHEEL
glored-0.1.1.dist-info/top_level.txt
glored-0.1.1.dist-info/RECORD
