Metadata-Version: 2.1
Name: glored
Version: 0.1.1
Summary: Redis client that runs as a unique global object within the library and supports asynchronous calls
Home-page: https://github.com/perrytec/glored.git
Author: perry
Author-email: noemail@example.com
Classifier: Programming Language :: Python :: 3
Classifier: Operating System :: OS Independent
Requires-Python: >=3.8
License-File: LICENSE
Requires-Dist: redis
Requires-Dist: hiredis
